client/client.py
watersmart/__init__.py
watersmart/usage_data_test.py
py_watersmart-0.1.5.dist-info/METADATA
py_watersmart-0.1.5.dist-info/WHEEL
py_watersmart-0.1.5.dist-info/entry_points.txt
py_watersmart-0.1.5.dist-info/top_level.txt
py_watersmart-0.1.5.dist-info/RECORD
