Metadata-Version: 2.1
Name: py-watersmart
Version: 0.1.5
Summary: Obtain water usage data from Watersmart.com
Author-email: "J.C. Jones" <jc@insufficient.coffee>
Project-URL: Repository, https://github.com/jcjones/py-watersmart.git
Project-URL: Issues, https://github.com/jcjones/py-watersmart/issues
Keywords: water meter
Classifier: Development Status :: 4 - Beta
Classifier: License :: OSI Approved :: Mozilla Public License 2.0 (MPL 2.0)
Classifier: Programming Language :: Python :: 3
Requires-Python: >=3.11
Requires-Dist: aiohttp
Requires-Dist: aiohttp-client-cache[sqlite]
Requires-Dist: async-timeout
Provides-Extra: test
Requires-Dist: pytest ; extra == 'test'
Requires-Dist: pytest-cov ; extra == 'test'
Requires-Dist: pytest-asyncio ; extra == 'test'
